
{
  "build": {
    "development": {
      "developmentClient": true,
      "distribution": "internal",
      "ios": {
        "buildNumber": "1"
      },
      "android": {
        "versionCode": 1
      }
    },
    "preview": {
      "distribution": "internal",
      "ios": {
        "buildNumber": "1"
      },
      "android": {
        "versionCode": 1
      }
    },
    "production": {
      "ios": {
        "buildNumber": "1"
      },
      "android": {
        "versionCode": 1
      }
    }
  },
  "submit": {
    "production": {}
  }
}
